ublcii/__about__.py
ublcii/__init__.py
ublcii/translate.py
ublcii/bots/botssys/sqlitedb/botsdb
ublcii/bots/config/__init__.py
ublcii/bots/config/bots.ini
ublcii/bots/config/settings.py
ublcii/bots/usersys/__init__.py
ublcii/bots/usersys/index.py
ublcii/bots/usersys/communicationscripts/__init__.py
ublcii/bots/usersys/communicationscripts/bots_file_in.py
ublcii/bots/usersys/communicationscripts/bots_file_out.py
ublcii/bots/usersys/grammars/__init__.py
ublcii/bots/usersys/grammars/xml/D16B_CII.py
ublcii/bots/usersys/grammars/xml/D16Brecords.py
ublcii/bots/usersys/grammars/xml/D16Bsequences.py
ublcii/bots/usersys/grammars/xml/UBL21_INVOICE.py
ublcii/bots/usersys/grammars/xml/UBL21records.py
ublcii/bots/usersys/grammars/xml/UBL21sequences.py
ublcii/bots/usersys/grammars/xml/__init__.py
ublcii/bots/usersys/mappings/__init__.py
ublcii/bots/usersys/mappings/xml/D16B_cii2xmlUBL21_invoice.py
ublcii/bots/usersys/mappings/xml/UBL21_invoice2xmlD16B_cii.py
ublcii/bots/usersys/mappings/xml/__init__.py
ublcii-1.0.2.dist-info/LICENSE
ublcii-1.0.2.dist-info/METADATA
ublcii-1.0.2.dist-info/WHEEL
ublcii-1.0.2.dist-info/entry_points.txt
ublcii-1.0.2.dist-info/top_level.txt
ublcii-1.0.2.dist-info/RECORD
