Metadata-Version: 2.1
Name: ublcii
Version: 1.0.2
Summary: Translate Invoice UBL 2.1 to/from CrossIndustryInvoice (CII) D16B
Home-page: https://converter-ubl-cii-invoice-xml.sourceforge.io
Author: Ludovic Watteaux
Author-email: ludovic.watteaux@gmail.com
License: GNU GPL v3.0
Project-URL: Source, https://github.com/Auratechcom/converter_ubl_cii_invoice_xml.git
Project-URL: Home, https://converter-ubl-cii-invoice-xml.sourceforge.io
Project-URL: Bug Reports, https://github.com/Auratechcom/converter_ubl_cii_invoice_xml/issues
Project-URL: Say Thanks!, http://www.auratechcom.fr/contact.htm
Project-URL: Say Thanks2!, https://www.edi-intelligentsia.com/contact/
Keywords: edi xml invoice ubl 2.1 CII CrossIndustryInvoice D16B
Platform: OS Independent (Written in an interpreted language)
Classifier: Development Status :: 5 - Production/Stable
Classifier: Operating System :: OS Independent
Classifier: Programming Language :: Python
Classifier: Programming Language :: Python :: 2
Classifier: Programming Language :: Python :: 2.7
Classifier: Programming Language :: Python :: 3
Classifier: Programming Language :: Python :: 3.4
Classifier: Programming Language :: Python :: 3.5
Classifier: Programming Language :: Python :: 3.6
Classifier: Programming Language :: Python :: 3.7
Classifier: Programming Language :: Python :: Implementation :: CPython
Classifier: Programming Language :: Python :: Implementation :: PyPy
Classifier: License :: OSI Approved :: GNU General Public License (GPL)
Classifier: Topic :: Office/Business
Classifier: Topic :: Office/Business :: Financial
Classifier: Topic :: Other/Nonlisted Topic
Classifier: Topic :: Communications
Classifier: Environment :: Console
Classifier: Environment :: Web Environment
Requires-Dist: setuptools
Requires-Dist: django (>=1.10)
Requires-Dist: bots-ediint (>=3.3.1rc1)
